nuqql/__init__.py
nuqql/account.py
nuqql/buddy.py
nuqql/main.py
nuqql/ui.py
nuqql/backend/__init__.py
nuqql/backend/backend.py
nuqql/backend/client.py
nuqql/backend/helpers.py
nuqql/backend/nuqqlbackend.py
nuqql/backend/parse.py
nuqql/backend/server.py
nuqql/config/__init__.py
nuqql/config/config.py
nuqql/config/configs.py
nuqql/config/winconfig.py
nuqql/conversation/__init__.py
nuqql/conversation/backendconversation.py
nuqql/conversation/buddyconversation.py
nuqql/conversation/conversation.py
nuqql/conversation/helper.py
nuqql/conversation/history.py
nuqql/conversation/logmessage.py
nuqql/conversation/mainconversation.py
nuqql/conversation/nuqqlconversation.py
nuqql/win/__init__.py
nuqql/win/inputwin.py
nuqql/win/listwin.py
nuqql/win/logwin.py
nuqql/win/win.py
nuqql-0.12.0.dist-info/LICENSE
nuqql-0.12.0.dist-info/METADATA
nuqql-0.12.0.dist-info/WHEEL
nuqql-0.12.0.dist-info/entry_points.txt
nuqql-0.12.0.dist-info/top_level.txt
nuqql-0.12.0.dist-info/RECORD
