Metadata-Version: 2.1
Name: nuqql
Version: 0.12.0
Summary: Command line instant messenger inspired by centericq/centerim
Home-page: https://github.com/hwipl/nuqql
Author: hwipl
Author-email: nuqql@hwipl.net
License: MIT
Platform: UNKNOWN
Classifier: Programming Language :: Python :: 3
Classifier: License :: OSI Approved :: MIT License
Requires-Python: >=3.6
License-File: LICENSE
